{
    "id": "493f62e64e0b4c58a28beb19a4306319",
    "title": "Modification of Adjectives and Adverbs",
    "exercises": [
        {
            "id": "b881c0c150d14359842a999f43f66f71",
            "title": "Modification of Adjectives and Adverbs",
            "questions": [
                {
                    "question": "It was ………………….. unpleasant experience.",
                    "description": "A little and a bit cannot be used with adjectives in attributive position.",
                    "answers": [
                        "a bit",
                        "a little",
                        "a rather"
                    ],
                    "correct": 2
                },
                {
                    "question": "She looked .......................unhappy.",
                    "description": "A little and a bit cannot be used with adjectives in attributive position.",
                    "answers": [
                        "a bit",
                        "a little",
                        "rather"
                    ],
                    "correct": 2
                },
                {
                    "question": "You are not ………………….. to be a soldier.",
                    "description": "Enough follows its adjective.",
                    "answers": [
                        "tall enough",
                        "enough tall",
                        "too tall"
                    ],
                    "correct": 0
                },
                {
                    "question": "I can’t tell you .....................… pleased I am about the result.",
                    "description": "We can use how before gradable adjectives and adverbs to add the idea of degree.",
                    "answers": [
                        "how",
                        "how much",
                        "what"
                    ],
                    "correct": 0
                },
                {
                    "question": "I thought the house was ………………….. small.",
                    "description": "We can use 'a little' before adjectives and adverbs expressing negative ideas.",
                    "answers": [
                        "a little",
                        "little",
                        "Either could be used here"
                    ],
                    "correct": 0
                },
                {
                    "question": "...................... can you speak English?",
                    "description": "We can use how before gradable adjectives and adverbs to add the idea of degree.",
                    "answers": [
                        "How",
                        "How well",
                        "Either could be used here"
                    ],
                    "correct": 0
                },
                {
                    "question": "He is …………………. creative.",
                    "description": "We use ‘not very’ to express a low degree. Little is not possible with this meaning.",
                    "answers": [
                        "not very",
                        "little",
                        "not little"
                    ],
                    "correct": 0
                },
                {
                    "question": "Her condition is ...................... serious.",
                    "description": "Very is not normally used with much before adjectives and adverbs.",
                    "answers": [
                        "very",
                        "very much",
                        "Either could be used here"
                    ],
                    "correct": 0
                },
                {
                    "question": "You should come …………………. quickly as you can.",
                    "description": "As is not used with much before adjectives ",
                    "answers": [
                        "as",
                        "as much",
                        "Either could be used here"
                    ],
                    "correct": 0
                },
                {
                    "question": "I don’t care ..................... expensive it is.",
                    "description": "How cannot be used with much before adjectives and adverbs.",
                    "answers": [
                        "how",
                        "how much",
                        "Either could be used here"
                    ],
                    "correct": 0
                },
                {
                    "question": "It is ………………… cold today.",
                    "description": "",
                    "answers": [
                        "very",
                        "very much",
                        "very little",
                        "All of these"
                    ],
                    "correct": 0
                },
                {
                    "question": "Today is ...................... colder than yesterday.",
                    "description": "Before comparative adjectives we can use very or very much.",
                    "answers": [
                        "very",
                        "very much",
                        "Either could be used here"
                    ],
                    "correct": 2
                }
            ]
        }
    ]
}