{
    "id": "7f80bfb3c2d644ee946f628923dbb64c",
    "title": "Grammar worksheet: prepositions",
    "exercises": [
        {
            "id": "a7aa92b5d0aa4032b7a7ac9f8d070dd6",
            "title": "Prepositions Exercise",
            "questions": [
                {
                    "question": "I acted according ......................... his advice.",
                    "description": "",
                    "answers": [
                        "on",
                        "to",
                        "with"
                    ],
                    "correct": 1
                },
                {
                    "question": "Death is the alternative .......................... submission.",
                    "description": "",
                    "answers": [
                        "for",
                        "to",
                        "of"
                    ],
                    "correct": 1
                },
                {
                    "question": "He jumped ——————– a conclusion not warranted by facts.",
                    "description": "",
                    "answers": [
                        "at",
                        "to",
                        "on"
                    ],
                    "correct": 1
                },
                {
                    "question": "He jumped ...................... my offer.",
                    "description": "",
                    "answers": [
                        "for",
                        "at",
                        "on",
                        "with"
                    ],
                    "correct": 1
                },
                {
                    "question": "Trust ........................ God and do what is right.",
                    "description": "",
                    "answers": [
                        "on",
                        "in",
                        "with"
                    ],
                    "correct": 1
                },
                {
                    "question": "You are wanting .............................. common sense.",
                    "description": "",
                    "answers": [
                        "on",
                        "in",
                        "for"
                    ],
                    "correct": 1
                },
                {
                    "question": "You must be prepared ........................... anything.",
                    "description": "",
                    "answers": [
                        "with",
                        "for",
                        "of"
                    ],
                    "correct": 1
                },
                {
                    "question": "I have no interest ........................... politics.",
                    "description": "",
                    "answers": [
                        "to",
                        "in",
                        "for"
                    ],
                    "correct": 1
                },
                {
                    "question": "They say the minister is partial ......................... his relatives.",
                    "description": "",
                    "answers": [
                        "with",
                        "to",
                        "for"
                    ],
                    "correct": 1
                },
                {
                    "question": "I take exception ......................... your remark.",
                    "description": "",
                    "answers": [
                        "for",
                        "to",
                        "with",
                        "at"
                    ],
                    "correct": 1
                },
                {
                    "question": "Let us proceed ............................. the work in hand.",
                    "description": "",
                    "answers": [
                        "to",
                        "with",
                        "for"
                    ],
                    "correct": 1
                },
                {
                    "question": "What you say is ......................... no consequence to me.",
                    "description": "",
                    "answers": [
                        "of",
                        "for",
                        "on"
                    ],
                    "correct": 0
                },
                {
                    "question": "He provided the poor .................... food and clothing.",
                    "description": "",
                    "answers": [
                        "with",
                        "to",
                        "for"
                    ],
                    "correct": 0
                }
            ]
        }
    ]
}