{
    "id": "9e95641ca7154ecbad1931ebeef45766",
    "title": "Infinitive complements worksheet",
    "exercises": [
        {
            "id": "8cc0f1fc78bb4c32ad71c902d0dc19b0",
            "title": "Infinitive Complements Exercise",
            "questions": [
                {
                    "question": "I have got a lot of letters ………………",
                    "description": "",
                    "answers": [
                        "to write",
                        "to be written"
                    ],
                    "correct": 1
                },
                {
                    "question": "The carpets ………………. are in the garage.",
                    "description": "",
                    "answers": [
                        "to clean",
                        "to be cleaned"
                    ],
                    "correct": 1
                },
                {
                    "question": "These vegetables are …………………",
                    "description": "",
                    "answers": [
                        "to chop",
                        "to be chopped"
                    ],
                    "correct": 1
                },
                {
                    "question": "These letters are ………………….",
                    "description": "",
                    "answers": [
                        "to post",
                        "to be posted"
                    ],
                    "correct": 1
                },
                {
                    "question": "The roof is ……………….. by Monday.",
                    "description": "",
                    "answers": [
                        "to repair",
                        "to be repaired"
                    ],
                    "correct": 1
                },
                {
                    "question": "There is a lot of work ………………….",
                    "description": "",
                    "answers": [
                        "to do",
                        "to be done",
                        "Either could be used here"
                    ],
                    "correct": 2
                },
                {
                    "question": "These are the names of the people .......................",
                    "description": "",
                    "answers": [
                        "to contact",
                        "to be contacted"
                    ],
                    "correct": 1
                },
                {
                    "question": "This form is ..................... in ink.",
                    "description": "",
                    "answers": [
                        "to fill in",
                        "to be filled",
                        "to be filled in"
                    ],
                    "correct": 2
                },
                {
                    "question": "You are .......................",
                    "description": "",
                    "answers": [
                        "to congratulate",
                        "to be congratulated"
                    ],
                    "correct": 1
                }
            ]
        }
    ]
}