{
    "id": "b4e3077ea7a34bb583639349715addaf",
    "title": "Phrasal verbs with take",
    "exercises": [
        {
            "id": "2e083437763f4c398f91b2cf036a86b5",
            "title": "Phrasal Verbs With Keep",
            "questions": [
                {
                    "question": "I was taken .............................. by her impertinence.",
                    "description": "When you are taken aback, you are shocked.",
                    "answers": [
                        "in",
                        "aback",
                        "out"
                    ],
                    "correct": 1
                },
                {
                    "question": "The child does not take ............................ either of his parents.",
                    "description": "To take after somebody is to resemble them in looks or behavior.",
                    "answers": [
                        "for",
                        "on",
                        "after"
                    ],
                    "correct": 2
                },
                {
                    "question": "If you have ten candies and take ............................... six, you are left with four.",
                    "description": "To take something away is to remove it or subtract it.",
                    "answers": [
                        "out",
                        "up",
                        "away"
                    ],
                    "correct": 2
                },
                {
                    "question": "The fact that the athlete had used performance enhancing drugs, took .............................. his achievements.",
                    "description": "To take away from something is to make it seem less valuable.",
                    "answers": [
                        "away",
                        "from",
                        "away from"
                    ],
                    "correct": 2
                },
                {
                    "question": "I took the shelves ................................... to clean them properly.",
                    "description": "To take something apart is to disassemble them.",
                    "answers": [
                        "apart",
                        "off",
                        "away"
                    ],
                    "correct": 0
                },
                {
                    "question": "A public outcry forced the minister to take ................................ his offensive comments.",
                    "description": "To take something back is to say that you didn't really mean what you had said.",
                    "answers": [
                        "back",
                        "down",
                        "off"
                    ],
                    "correct": 0
                },
                {
                    "question": "Please take .................................... my address and phone number.",
                    "description": "Take down can mean write down. ",
                    "answers": [
                        "off",
                        "up",
                        "down"
                    ],
                    "correct": 2
                },
                {
                    "question": "Don't take him ............................. an idiot.",
                    "description": "\r\nTo take somebody for an idiot is to regard them as an idiot.\r\n",
                    "answers": [
                        "as",
                        "in",
                        "for"
                    ],
                    "correct": 2
                },
                {
                    "question": "I took .............................. a pup last month and now he is my best buddy.",
                    "description": "To take in somebody is to give them shelter.",
                    "answers": [
                        "up",
                        "in",
                        "on"
                    ],
                    "correct": 1
                },
                {
                    "question": "I took .............................. every word they uttered. It was such a mesmerizing performance.",
                    "description": "To take in something is to absorb it or understand it.",
                    "answers": [
                        "in",
                        "off",
                        "up"
                    ],
                    "correct": 0
                },
                {
                    "question": "Although the airplane took .................................... 30 minutes late, it arrived on time.",
                    "description": "When an airplane takes off, it begins to fly.",
                    "answers": [
                        "off",
                        "out",
                        "over"
                    ],
                    "correct": 0
                },
                {
                    "question": "I am too busy to take .............................. any extra work.",
                    "description": "To take on a job is to accept it.",
                    "answers": [
                        "on",
                        "over",
                        "in"
                    ],
                    "correct": 0
                }
            ]
        },
        {
            "id": "0cf37cc1b3914b788be9654a569aeaef",
            "title": "Phrasal Verbs With Take",
            "questions": [
                {
                    "question": "Please take your shoes .......................... before entering the temple.",
                    "description": "To take a piece of clothing off is to remove it.",
                    "answers": [
                        "out",
                        "up",
                        "off"
                    ],
                    "correct": 2
                },
                {
                    "question": "Raj has taken ......................... scuba diving.",
                    "description": "To take up something is to start a new hobby or activity. ",
                    "answers": [
                        "for",
                        "in",
                        "up"
                    ],
                    "correct": 2
                },
                {
                    "question": "Selena takes ............................. her grandmother.",
                    "description": "To take after somebody is to resemble them.",
                    "answers": [
                        "on",
                        "up",
                        "after"
                    ],
                    "correct": 2
                },
                {
                    "question": "The minister was forced to take his offensive remarks .........................",
                    "description": "To take something back is to withdraw a statement.",
                    "answers": [
                        "down",
                        "off",
                        "back"
                    ],
                    "correct": 2
                },
                {
                    "question": "This blouse is too loose for you. You must take it .........................",
                    "description": "To take a garment in is to make it tighter.",
                    "answers": [
                        "up",
                        "down",
                        "in"
                    ],
                    "correct": 2
                },
                {
                    "question": "As our business expands, we will take more people .............................",
                    "description": "To take somebody on is to employ them.",
                    "answers": [
                        "in",
                        "on",
                        "over"
                    ],
                    "correct": 1
                },
                {
                    "question": "I don’t think I can take ........................... this responsibility.",
                    "description": "To take on a task is to undertake it.",
                    "answers": [
                        "out",
                        "in",
                        "on"
                    ],
                    "correct": 2
                },
                {
                    "question": "You might have had a bad day at work but you can’t take it .............................. on me.",
                    "description": "To take it out on somebody is to relieve your frustration by treating them badly.",
                    "answers": [
                        "up",
                        "with",
                        "out"
                    ],
                    "correct": 2
                },
                {
                    "question": "After his father died, he took ............................ their family business.",
                    "description": "To take over something is to assume responsibility for it.",
                    "answers": [
                        "in",
                        "out",
                        "over"
                    ],
                    "correct": 2
                },
                {
                    "question": "The girl took ........................... her foster parents almost instantly.",
                    "description": "To take to somebody is to like them.",
                    "answers": [
                        "on",
                        "to",
                        "in"
                    ],
                    "correct": 1
                },
                {
                    "question": "As soon as we saw the leopard, we took ......................... our heels.",
                    "description": "To take to one’s heels is to run to escape danger.",
                    "answers": [
                        "on",
                        "over",
                        "to"
                    ],
                    "correct": 2
                },
                {
                    "question": "He took ............................ farming after retirement.",
                    "description": "To take up something is to undertake it. ",
                    "answers": [
                        "on",
                        "in",
                        "up"
                    ],
                    "correct": 2
                }
            ]
        }
    ]
}