{
    "id": "be462be9613c4885a0b24c7be5422a04",
    "title": "Enough exercise",
    "exercises": [
        {
            "id": "49bca84018c745beaa0a2109ca8631f5",
            "title": "Enough Exercise",
            "questions": [
                {
                    "question": "My aunt is rich enough ………………… buy a Ferrari.",
                    "description": "",
                    "answers": [
                        "to",
                        "so she can"
                    ],
                    "correct": 0
                },
                {
                    "question": "We haven’t got ………………….. to go on holiday.",
                    "description": "",
                    "answers": [
                        "many money",
                        "money enough",
                        "enough money"
                    ],
                    "correct": 2
                },
                {
                    "question": "He can’t run very fast. He is not ………………….",
                    "description": "",
                    "answers": [
                        "enough fit",
                        "fit enough"
                    ],
                    "correct": 1
                },
                {
                    "question": "The meat is good enough …………………. buy.",
                    "description": "",
                    "answers": [
                        "to",
                        "that we can",
                        "for us to"
                    ],
                    "correct": 2
                },
                {
                    "question": "She is not .......................................... to be a grandmother.",
                    "description": "",
                    "answers": [
                        "enough old",
                        "old enough"
                    ],
                    "correct": 1
                },
                {
                    "question": "The day was warm enough ..........................................",
                    "description": "",
                    "answers": [
                        "so that we could go out",
                        "that we could go out",
                        "for us to go out"
                    ],
                    "correct": 2
                },
                {
                    "question": "The problem was ....................................... for me to solve.",
                    "description": "",
                    "answers": [
                        "enough easy",
                        "easy enough"
                    ],
                    "correct": 1
                },
                {
                    "question": "They are rich enough .................................... a luxury car.",
                    "description": "",
                    "answers": [
                        "that they can",
                        "to buy"
                    ],
                    "correct": 1
                },
                {
                    "question": "William plays ............................................. for his team to win.",
                    "description": "",
                    "answers": [
                        "enough cleverly",
                        "cleverly enough"
                    ],
                    "correct": 1
                }
            ]
        }
    ]
}