{
    "id": "f582005bf4234cee8fff825dc34c352c",
    "title": "Too and enough",
    "exercises": [
        {
            "id": "dd5b02abc73f443694b53b268869d2a1",
            "title": "Too And Enough",
            "questions": [
                {
                    "question": "There were ………………. many letters to write.",
                    "description": "",
                    "answers": [
                        "too",
                        "enough",
                        "Either could be used here"
                    ],
                    "correct": 0
                },
                {
                    "question": "The tea was ………………. It almost burnt my tongue.",
                    "description": "",
                    "answers": [
                        "too hot",
                        "hot too",
                        "hot enough"
                    ],
                    "correct": 0
                },
                {
                    "question": "Should I turn the heating on? I think the room isn’t ……………..",
                    "description": "",
                    "answers": [
                        "too cool",
                        "hot enough",
                        "cool enough",
                        "enough hot"
                    ],
                    "correct": 1
                },
                {
                    "question": "I didn’t buy the watch because it was ……………….",
                    "description": "",
                    "answers": [
                        "enough expensive",
                        "too expensive",
                        "expensive enough"
                    ],
                    "correct": 1
                },
                {
                    "question": "We didn’t buy the house because it was not …………………..",
                    "description": "",
                    "answers": [
                        "too spacious",
                        "enough spacious",
                        "spacious enough"
                    ],
                    "correct": 2
                },
                {
                    "question": "Do you have a smaller size? This jacket is …………….. for me.",
                    "description": "",
                    "answers": [
                        "enough large",
                        "large enough",
                        "too large"
                    ],
                    "correct": 2
                },
                {
                    "question": "Some tablet computers are ………………… to fit inside your pocket.",
                    "description": "",
                    "answers": [
                        "too small",
                        "enough small",
                        "small enough"
                    ],
                    "correct": 2
                },
                {
                    "question": "The bag was ………………….. for me to lift.",
                    "description": "",
                    "answers": [
                        "enough heavy",
                        "too heavy",
                        "heavy enough"
                    ],
                    "correct": 1
                },
                {
                    "question": "I was ………………. to talk to them.",
                    "description": "",
                    "answers": [
                        "enough busy",
                        "busy enough",
                        "too busy"
                    ],
                    "correct": 2
                },
                {
                    "question": "I haven’t got ………………. to take a vacation this year.",
                    "description": "",
                    "answers": [
                        "too much time",
                        "time enough",
                        "enough time"
                    ],
                    "correct": 2
                }
            ]
        },
        {
            "id": "6c67f8bc4fe74e308bc37f8d8ca5ba88",
            "title": "Too And Enough",
            "questions": [
                {
                    "question": "There were ……………….. many questions to answer so I ran out of time.",
                    "description": "",
                    "answers": [
                        "too",
                        "so"
                    ],
                    "correct": 0
                },
                {
                    "question": "She is old ………………… to make her own bed now.",
                    "description": "",
                    "answers": [
                        "enough",
                        "too"
                    ],
                    "correct": 0
                },
                {
                    "question": "The tea was ………………….. hot for me to drink.",
                    "description": "",
                    "answers": [
                        "too",
                        "so"
                    ],
                    "correct": 0
                },
                {
                    "question": "The room was …………………. so I turned the heating off.",
                    "description": "",
                    "answers": [
                        "too enough",
                        "hot enough"
                    ],
                    "correct": 1
                },
                {
                    "question": "I didn’t buy the laptop because it was …………………",
                    "description": "",
                    "answers": [
                        "enough expensive",
                        "too expensive"
                    ],
                    "correct": 1
                },
                {
                    "question": "The shirt was ………………. so I didn’t buy it.",
                    "description": "",
                    "answers": [
                        "too small",
                        "small enough"
                    ],
                    "correct": 0
                },
                {
                    "question": "The tablet is ……………… to fit inside your pocket.",
                    "description": "",
                    "answers": [
                        "too small",
                        "small enough"
                    ],
                    "correct": 1
                },
                {
                    "question": "It is ………………. to start a new lesson now.",
                    "description": "",
                    "answers": [
                        "too late",
                        "late enough"
                    ],
                    "correct": 0
                },
                {
                    "question": "I haven’t got …………………. to buy the tickets.",
                    "description": "",
                    "answers": [
                        "too money",
                        "enough money"
                    ],
                    "correct": 1
                },
                {
                    "question": "It was ……………… to carry.",
                    "description": "",
                    "answers": [
                        "too light",
                        "light enough"
                    ],
                    "correct": 1
                }
            ]
        }
    ]
}